{

"Base" :
{
    "DESC" : "base layer",
    "PARENT" : "",
    "LEVEL" : 0,
    "VARS" :
        [
            ["id", "uint32_t", "0"],
            ["name", "char[1024]", "\"\""],
            ["inputCount", "int", "0"],
            ["input0", "char[1024]", "\"\""],
            ["input1", "char[1024]", "\"\""],
            ["input2", "char[1024]", "\"\""],
            ["input3", "char[1024]", "\"\""],
            ["input4", "char[1024]", "\"\""],
            ["input5", "char[1024]", "\"\""],
            ["input6", "char[1024]", "\"\""],
            ["input7", "char[1024]", "\"\""],
            ["outputCount", "int", "0"],
            ["output0", "char[1024]", "\"\""],
            ["output1", "char[1024]", "\"\""],
            ["output2", "char[1024]", "\"\""],
            ["output3", "char[1024]", "\"\""],
            ["output4", "char[1024]", "\"\""],
            ["output5", "char[1024]", "\"\""],
            ["output6", "char[1024]", "\"\""],
            ["output7", "char[1024]", "\"\""],
            ["propDownCount", "int", "0"],
            ["propDown0", "bool", "false"],
            ["propDown1", "bool", "false"],
            ["propDown2", "bool", "false"],
            ["propDown3", "bool", "false"],
            ["propDown4", "bool", "false"],
            ["propDown5", "bool", "false"],
            ["propDown6", "bool", "false"],
            ["propDown7", "bool", "false"],
            ["donate", "bool", "false"],
            ["receive", "bool", "false"],
            ["donatorID", "int", "0"]
        ]
},

"Conv" : 
{
    "DESC" : "convolution layer",
    "PARENT" : "Base",
    "LEVEL" : 1,
    "VARS" : 
        [   
            ["filterDimRows", "uint32_t", "0"],
            ["filterDimCols", "uint32_t", "0"],
            ["filterDimChannels", "uint32_t", "0"],
            ["filterDimFilters", "uint32_t", "0"],
            ["filterDimPads", "uint32_t", "0"],
            ["filterDimStrides", "uint32_t", "1"],
            ["weightUpdateParamLRMulti", "float", "1.0"],
            ["weightUpdateParamDecayMulti", "float", "0.0"],
            ["biasUpdateParamLRMulti", "float", "1.0"],
            ["biasUpdateParamDecayMulti", "float", "0.0"],
            ["weightFillerType", "int", "ParamFillerType::Constant"],
            ["weightFillerValue", "float", "0.0"],
            ["biasFillerType", "int", "ParamFillerType::Constant"],
            ["biasFillerValue", "float", "0.0"],
            ["deconv", "bool", "false"],
            ["deconvExtraCell", "int", "0"]
        ]
}

}
